pyglinet/__init__.py
pyglinet/decorators.py
pyglinet/exceptions.py
pyglinet/glinet.py
pyglinet/glinet_api.py
pyglinet/utils.py
pyglinet/api/api_description.json
python_glinet-0.8.2.dist-info/licenses/LICENSE
python_glinet-0.8.2.dist-info/METADATA
python_glinet-0.8.2.dist-info/WHEEL
python_glinet-0.8.2.dist-info/top_level.txt
python_glinet-0.8.2.dist-info/RECORD
