Metadata-Version: 2.4
Name: python-glinet
Version: 0.8.2
Summary: Python3 client for Gl.Inet LUCI API firmware 4.0 onwards.
Author-email: Tomtana <python@tomtana.net>
License:                     GNU GENERAL PUBLIC LICENSE
Project-URL: Bug Tracker, https://github.com/tomtana/python-glinet/issues
Project-URL: Documentation, https://tomtana.github.io/python-glinet
Project-URL: Source, https://github.com/tomtana/python-glinet
Classifier: Programming Language :: Python :: 3
Classifier: Operating System :: OS Independent
Classifier: License :: OSI Approved :: GNU General Public License v3 or later (GPLv3+)
Requires-Python: >=3.9
License-File: LICENSE
Requires-Dist: ipython>=8.18.1
Requires-Dist: passlib>=1.7.4
Requires-Dist: requests>=2.32.5
Requires-Dist: tabulate>=0.9.0
Dynamic: license-file
